AUTHORS
LICENSE
MANIFEST.in
README.rst
requirements.pip
setup.cfg
setup.py
pyjs/__Future__.py
pyjs/__Pyjamas__.py
pyjs/__init__.py
pyjs/browser.py
pyjs/browser.txt
pyjs/linker.py
pyjs/options.py
pyjs/pyjampiler.py
pyjs/pyjsbuild.1
pyjs/pyjstest.py
pyjs/sm.py
pyjs/sm.txt
pyjs/testing.py
pyjs/tests.py
pyjs/translator.py
pyjs/translator.txt
pyjs/translator_dict.py
pyjs/translator_proto.py
pyjs/util.py
pyjs/util.txt
pyjs/boilerplate/all.cache.html
pyjs/boilerplate/app.html
pyjs/boilerplate/home.nocache.html
pyjs/boilerplate/index.html
pyjs/boilerplate/mod.cache.html
pyjs/boilerplate/pygwt.js
pyjs/boilerplate/pyjampiler_wrapper.js.tmpl
pyjs/builtin/__builtin__.py
pyjs/builtin/__builtin__.py.in
pyjs/builtin/__init__.py
pyjs/builtin/mkbuiltin.py
pyjs/builtin/pyjslib.py
pyjs/builtin/pyjslib.pyv8.py
pyjs/builtin/pyjslib.spidermonkey.py
pyjs/builtin/public/_pyjs.js
pyjs/builtin/public/bootstrap.js
pyjs/builtin/public/bootstrap_progress.js
pyjs/jsonrpc/README.txt
pyjs/jsonrpc/__init__.py
pyjs/jsonrpc/cgihandler/README.txt
pyjs/jsonrpc/cgihandler/__init__.py
pyjs/jsonrpc/cherrypy/__init__.py
pyjs/jsonrpc/cherrypy/jsonrpc.py
pyjs/jsonrpc/django/__init__.py
pyjs/jsonrpc/django/jsonformprocessor.py
pyjs/jsonrpc/django/jsonrpc.py
pyjs/jsonrpc/mongrel2/__init__.py
pyjs/jsonrpc/mongrel2/example.py
pyjs/jsonrpc/mongrel2/testjsonrpc.py
pyjs/jsonrpc/web2py/README.txt
pyjs/jsonrpc/web2py/__init__.py
pyjs/jsonrpc/web2py/jsonrpc.py
pyjs/lib/StringIO.py
pyjs/lib/__init__.py
pyjs/lib/_random.py
pyjs/lib/_weakrefset.py
pyjs/lib/base64.py
pyjs/lib/binascii.py
pyjs/lib/cgi.py
pyjs/lib/codecs.py
pyjs/lib/csv.py
pyjs/lib/datetime.py
pyjs/lib/errno.py
pyjs/lib/genericpath.py
pyjs/lib/getopt.py
pyjs/lib/gettext.py
pyjs/lib/htmlentitydefs.py
pyjs/lib/imp.py
pyjs/lib/ipaddr.py
pyjs/lib/json.py
pyjs/lib/math.py
pyjs/lib/md5.py
pyjs/lib/operator.py
pyjs/lib/pyjd.py
pyjs/lib/pyjspath.py
pyjs/lib/random.py
pyjs/lib/re.py
pyjs/lib/sets.py
pyjs/lib/socket.py
pyjs/lib/stat.py
pyjs/lib/string.py
pyjx.egg-info/PKG-INFO
pyjx.egg-info/SOURCES.txt
pyjx.egg-info/dependency_links.txt
pyjx.egg-info/entry_points.txt
pyjx.egg-info/not-zip-safe
pyjx.egg-info/top_level.txt
